check_dns_sync/__init__.py
check_dns_sync/check_dns_sync.py
check_dns_sync/tests/__init__.py
check_dns_sync/tests/test_check_dns_sync.py
check_dns_sync-0.1.dist-info/DESCRIPTION.rst
check_dns_sync-0.1.dist-info/METADATA
check_dns_sync-0.1.dist-info/RECORD
check_dns_sync-0.1.dist-info/WHEEL
check_dns_sync-0.1.dist-info/entry_points.txt
check_dns_sync-0.1.dist-info/metadata.json
check_dns_sync-0.1.dist-info/top_level.txt
paulla/__init__.py
paulla/check_dns_sync/__init__.py
paulla/check_dns_sync/check_dns_sync.py
paulla/check_dns_sync/tests/__init__.py
paulla/check_dns_sync/tests/test_check_dns_sync.py
